mbg_exercise_client/__init__.py
mbg_exercise_client/cutie.py
mbg_exercise_client/cutie_example.py
mbg_exercise_client-0.2.4.dist-info/LICENSE
mbg_exercise_client-0.2.4.dist-info/METADATA
mbg_exercise_client-0.2.4.dist-info/WHEEL
mbg_exercise_client-0.2.4.dist-info/entry_points.txt
mbg_exercise_client-0.2.4.dist-info/top_level.txt
mbg_exercise_client-0.2.4.dist-info/RECORD
