Metadata-Version: 2.1
Name: mbg-exercise-client
Version: 0.2.4
Summary: Tool for lauching jupyter from docker containers
Author: Kasper Munch
Author-email: kaspermunch@birc.au.dk
Classifier: Programming Language :: Python :: 3
Classifier: License :: OSI Approved :: MIT License
Classifier: Operating System :: OS Independent
Requires-Python: >=3.8
License-File: LICENSE
Requires-Dist: requests
Requires-Dist: packaging
Requires-Dist: colorama
Requires-Dist: readchar
